  {
    "@context": "http://iiif.io/api/presentation/2/context.json",
    "id":"https://raw.githubusercontent.com/OscarSeip/oscarseip.github.io/sCRSn2ThGK_Annotations/Manifests/sCRSn2ThGK/annotations/f0009.json",
    "type": "Annotation",
    "motivation": "commenting",
    "body": 
      {
        "@type": "TextualBody",
        "format": "text/plain",
        "chars": "Theatrum vitae humanae"
      },
    "target": "https://api.digitale-sammlungen.de/iiif/presentation/v2/bsb11196453/canvas/9",
  }